pystatar/__init__.py
pystatar/egen/__init__.py
pystatar/egen/_version.py
pystatar/pdtab/__init__.py
pystatar/pdtab/_version.py
pystatar/pdtab/core.py
pystatar/winsor2/__init__.py
pystatar-0.4.0.dist-info/licenses/LICENSE
pystatar-0.4.0.dist-info/METADATA
pystatar-0.4.0.dist-info/WHEEL
pystatar-0.4.0.dist-info/top_level.txt
pystatar-0.4.0.dist-info/RECORD
