Metadata-Version: 2.4
Name: pystatar
Version: 0.4.0
Summary: PyStataR aims to recreate and significantly enhance the top and most frequently used Stata commands in Python, transforming them into the most powerful and user-friendly statistical tools for academic research. Our goal is to not just replicate Stata's functionality, but to expand and improve upon it, leveraging Python's ecosystem to create superior research tools.
Author-email: Bryce Wang <brycew6m@stanford.edu>
Maintainer-email: Bryce Wang <brycew6m@stanford.edu>
License-Expression: MIT
Project-URL: Homepage, https://github.com/brycewang-stanford/PyStataR
Project-URL: Repository, https://github.com/brycewang-stanford/PyStataR
Project-URL: Documentation, https://github.com/brycewang-stanford/PyStataR/docs
Project-URL: Bug Tracker, https://github.com/brycewang-stanford/PyStataR/issues
Keywords: stata,pandas,econometrics,statistics,data-analysis,tabulate,egen,winsor,cross-tabulation,pyegen,pywinsor2,pdtab,data-manipulation,winsorizing,frequency-analysis,outreg,pyoutreg,regression-tables,outreg2,model-output,research-tools
Classifier: Development Status :: 4 - Beta
Classifier: Intended Audience :: Science/Research
Classifier: Operating System :: OS Independent
Classifier: Programming Language :: Python :: 3
Classifier: Programming Language :: Python :: 3.8
Classifier: Programming Language :: Python :: 3.9
Classifier: Programming Language :: Python :: 3.10
Classifier: Programming Language :: Python :: 3.11
Classifier: Programming Language :: Python :: 3.12
Classifier: Programming Language :: Python :: 3.13
Classifier: Topic :: Scientific/Engineering
Classifier: Topic :: Scientific/Engineering :: Information Analysis
Classifier: Topic :: Software Development :: Libraries :: Python Modules
Requires-Python: >=3.8
License-File: LICENSE
Requires-Dist: pandas>=1.3.0
Requires-Dist: numpy>=1.20.0
Requires-Dist: scipy>=1.7.0
Requires-Dist: pyegen>=0.2.0
Requires-Dist: pywinsor2>=0.4.0
Requires-Dist: pdtab>=0.1.0
Requires-Dist: pyoutreg>=0.1.0
Provides-Extra: dev
Requires-Dist: pytest>=6.0; extra == "dev"
Requires-Dist: pytest-cov; extra == "dev"
Requires-Dist: black; extra == "dev"
Requires-Dist: isort; extra == "dev"
Requires-Dist: flake8; extra == "dev"
Requires-Dist: mypy; extra == "dev"
Requires-Dist: pre-commit; extra == "dev"
Provides-Extra: docs
Requires-Dist: sphinx>=4.0; extra == "docs"
Requires-Dist: sphinx-rtd-theme; extra == "docs"
Requires-Dist: nbsphinx; extra == "docs"
Requires-Dist: pandoc; extra == "docs"
Provides-Extra: test
Requires-Dist: pytest>=6.0; extra == "test"
Requires-Dist: pytest-cov; extra == "test"
Requires-Dist: pytest-xdist; extra == "test"
Dynamic: license-file
